cnxcommon/__init__.py
cnxcommon/_version.py
cnxcommon/ident_hash.py
cnxcommon/urlslug.py
cnxcommon/utils.py
tests/__init__.py
tests/test_ident_hash.py
tests/test_urlslug.py
cnx_common-1.3.6.dist-info/LICENSE.txt
cnx_common-1.3.6.dist-info/METADATA
cnx_common-1.3.6.dist-info/WHEEL
cnx_common-1.3.6.dist-info/top_level.txt
cnx_common-1.3.6.dist-info/RECORD
