Metadata-Version: 2.1
Name: cnx-common
Version: 1.3.6
Summary: A library of utilities used across CNX applications.
Home-page: https://github.com/openstax/cnx-common
Author: Connexions team
Author-email: info@cnx.org
License: AGPL, See also LICENSE.txt
Platform: UNKNOWN
Requires-Dist: python-slugify (==4.0.1)
Provides-Extra: test
Requires-Dist: pytest ; extra == 'test'
Requires-Dist: pytest-cov ; extra == 'test'
Requires-Dist: pytest-runner ; extra == 'test'
